db2py/__init__.py
db2py-0.0.1.data/scripts/db2py
db2py-0.0.1.dist-info/METADATA
db2py-0.0.1.dist-info/WHEEL
db2py-0.0.1.dist-info/top_level.txt
db2py-0.0.1.dist-info/RECORD
