Metadata-Version: 2.1
Name: db2py
Version: 0.0.1
Summary: A Python interface to create and edit databases, and to hash passwords. 
Home-page: https://pypi.org/project/db2py
Author: Sandra Mattar
Author-email: sandrawmattar1@gmail.com
License: UNKNOWN
Platform: UNKNOWN
